spacunhas/__init__.py
spacunhas/complexcoherence.py
spacunhas/dispersioncurve.py
spacunhas/environment.py
spacunhas/readdata.py
spacunhas/spaccoefficient.py
spacunhas/windowing.py
spac_unhas_ahmadfauzy02-0.1.dist-info/LICENSE
spac_unhas_ahmadfauzy02-0.1.dist-info/METADATA
spac_unhas_ahmadfauzy02-0.1.dist-info/WHEEL
spac_unhas_ahmadfauzy02-0.1.dist-info/top_level.txt
spac_unhas_ahmadfauzy02-0.1.dist-info/RECORD
