Metadata-Version: 2.2
Name: spac-unhas_ahmadfauzy02
Version: 0.1
Summary: SPAC processing
Home-page: https://github.com/yourusername/spacunhas
Author: Ahmad Fauzy
Author-email: Ahmad Fauzy Arif <ahmadfauzyarif@gmail.com>
License: MIT
Project-URL: Homepage, https://github.com/ahmadfauzy02/spac-unhas
Project-URL: Issues, https://github.com/ahmadfauzy02/spac-unhas/issues
Classifier: Programming Language :: Python :: 3.12
Classifier: Operating System :: OS Independent
Requires-Python: >=3.12
License-File: LICENSE
Requires-Dist: setuptools
Requires-Dist: scipy
Requires-Dist: obspy
Requires-Dist: pandas
Requires-Dist: numpy
Requires-Dist: matplotlib
Dynamic: author
Dynamic: home-page
Dynamic: requires-python
